mistai_grpc/__init__.py
mistai_grpc/app.py
mistai_grpc-0.1.0.dist-info/LICENSE
mistai_grpc-0.1.0.dist-info/METADATA
mistai_grpc-0.1.0.dist-info/WHEEL
mistai_grpc-0.1.0.dist-info/top_level.txt
mistai_grpc-0.1.0.dist-info/RECORD
