Metadata-Version: 2.1
Name: mistai_grpc
Version: 0.1.0
Summary: Core gRPC Modules for mist.ai
Author: Team mist.ai
Author-email: sandev.20@cse.mrt.ac.lk
Keywords: python,mist.ai,template
Classifier: Development Status :: 1 - Planning
Classifier: Intended Audience :: Developers
Classifier: Programming Language :: Python :: 3
Classifier: Operating System :: Unix
Classifier: Operating System :: MacOS :: MacOS X
Classifier: Operating System :: Microsoft :: Windows
License-File: LICENSE
